<?xml version="1.0" encoding="UTF-8"?>
<!--
Created with Funkin Packer v0.1.3 https://neeeoo.github.io/funkin-packer/
-->
<TextureAtlas imagePath="securit.png" width="1256" height="162">
	<SubTexture name="idle0000" x="246" y="0" width="89" height="137" frameX="-14" frameY="-26" frameWidth="135" frameHeight="170"/>
	<SubTexture name="idle0001" x="345" y="0" width="89" height="137" frameX="-13" frameY="-26" frameWidth="135" frameHeight="170"/>
	<SubTexture name="idle0002" x="444" y="0" width="89" height="140" frameX="-12" frameY="-23" frameWidth="135" frameHeight="170"/>
	<SubTexture name="idle0003" x="543" y="0" width="91" height="140" frameX="-12" frameY="-23" frameWidth="135" frameHeight="170"/>
	<SubTexture name="l0000" x="741" y="0" width="97" height="145" frameX="-1" frameY="-18" frameWidth="135" frameHeight="170"/>
	<SubTexture name="l0001" x="848" y="0" width="93" height="146" frameX="-5" frameY="-17" frameWidth="135" frameHeight="170"/>
	<SubTexture name="u0000" x="1160" y="0" width="96" height="162" frameX="-10" frameY="-1" frameWidth="135" frameHeight="170"/>
	<SubTexture name="u0001" x="1050" y="0" width="100" height="155" frameX="-8" frameY="-8" frameWidth="135" frameHeight="170"/>
	<SubTexture name="d0000" x="0" y="0" width="114" height="118" frameX="-20" frameY="-51" frameWidth="136" frameHeight="171"/>
	<SubTexture name="d0001" x="124" y="0" width="112" height="123" frameX="-20" frameY="-46" frameWidth="136" frameHeight="171"/>
	<SubTexture name="r0000" x="951" y="0" width="89" height="150" frameX="-24" frameY="-14" frameWidth="135" frameHeight="170"/>
	<SubTexture name="r0001" x="644" y="0" width="87" height="143" frameX="-23" frameY="-20" frameWidth="135" frameHeight="170"/>
</TextureAtlas>